aws/osml/features/__init__.py
aws/osml/features/feature_index.py
aws/osml/features/geolocation.py
aws/osml/features/imaged_feature_property_accessor.py
aws/osml/formats/__init__.py
aws/osml/formats/sicd/__init__.py
aws/osml/formats/sicd/models/__init__.py
aws/osml/formats/sicd/models/sicd_v1_2_1.py
aws/osml/formats/sicd/models/sicd_v1_3_0.py
aws/osml/formats/sidd/__init__.py
aws/osml/formats/sidd/models/__init__.py
aws/osml/formats/sidd/models/sfa.py
aws/osml/formats/sidd/models/sicommon_types.py
aws/osml/formats/sidd/models/sicommon_types_v1_0.py
aws/osml/formats/sidd/models/sidd_v1_0_0.py
aws/osml/formats/sidd/models/sidd_v2_0_0.py
aws/osml/formats/sidd/models/sidd_v3_0_0.py
aws/osml/formats/sidd/models/external/__init__.py
aws/osml/formats/sidd/models/external/ism/__init__.py
aws/osml/formats/sidd/models/external/ism/schema/__init__.py
aws/osml/formats/sidd/models/external/ism/schema/cvegenerated/__init__.py
aws/osml/formats/sidd/models/external/ism/schema/cvegenerated/cvenum_ism25_x.py
aws/osml/formats/sidd/models/external/ism/schema/cvegenerated/cvenum_ismclassification_all.py
aws/osml/formats/sidd/models/external/ism/schema/cvegenerated/cvenum_ismcomplies_with.py
aws/osml/formats/sidd/models/external/ism/schema/cvegenerated/cvenum_ismdissem.py
aws/osml/formats/sidd/models/external/ism/schema/cvegenerated/cvenum_ismfgiopen.py
aws/osml/formats/sidd/models/external/ism/schema/cvegenerated/cvenum_ismfgiprotected.py
aws/osml/formats/sidd/models/external/ism/schema/cvegenerated/cvenum_ismnon_ic.py
aws/osml/formats/sidd/models/external/ism/schema/cvegenerated/cvenum_ismnon_uscontrols.py
aws/osml/formats/sidd/models/external/ism/schema/cvegenerated/cvenum_ismowner_producer.py
aws/osml/formats/sidd/models/external/ism/schema/cvegenerated/cvenum_ismrel_to.py
aws/osml/formats/sidd/models/external/ism/schema/cvegenerated/cvenum_ismscicontrols.py
aws/osml/formats/sidd/models/external/ism/schema/cvegenerated/cvenum_ismsource_marked.py
osml_imagery_toolkit-1.4.2.dist-info/LICENSE
osml_imagery_toolkit-1.4.2.dist-info/METADATA
osml_imagery_toolkit-1.4.2.dist-info/WHEEL
osml_imagery_toolkit-1.4.2.dist-info/top_level.txt
osml_imagery_toolkit-1.4.2.dist-info/RECORD
