Metadata-Version: 2.1
Name: osml-imagery-toolkit
Version: 1.4.2
Summary: Toolkit to work with imagery collected by satellites and UAVs
Author: Amazon Web Services
Author-email: aws-osml-admin@amazon.com
License: 
Project-URL: Source, https://github.com/aws-solutions-library-samples/osml-imagery-toolkit
Project-URL: Tracker, https://github.com/aws-solutions-library-samples/osml-imagery-toolkit/issues
Classifier: Programming Language :: Python :: 3
Classifier: Operating System :: OS Independent
Requires-Python: >=3.9
License-File: LICENSE
Requires-Dist: numpy>=1.23.0
Requires-Dist: scikit-optimize>=0.9.0
Requires-Dist: opencv-python-headless>=4.9.0
Requires-Dist: cachetools>=5.3.2
Requires-Dist: geojson>=3.1.0
Requires-Dist: pyproj>=3.6.1
Requires-Dist: shapely>=2.0.2
Requires-Dist: omegaconf==2.3.0; python_version < "3.10.0"
Requires-Dist: xsdata>=24.1
Requires-Dist: defusedxml>=0.7.1
Provides-Extra: gdal
Requires-Dist: gdal<3.10,>=3.7.0; extra == "gdal"
Provides-Extra: test
Requires-Dist: tox; extra == "test"
